lsst/__init__.py
lsst/ctrl/__init__.py
lsst/ctrl/platform/__init__.py
lsst/ctrl/platform/s3df/__init__.py
lsst/ctrl/platform/s3df/etc/__init__.py
lsst/ctrl/platform/s3df/etc/config/__init__.py
lsst/ctrl/platform/s3df/etc/config/execConfig.py
lsst/ctrl/platform/s3df/etc/config/slurmConfig.py
lsst/ctrl/platform/s3df/etc/templates/__init__.py
lsst/ctrl/platform/s3df/etc/templates/allocation.sh.template
lsst/ctrl/platform/s3df/etc/templates/dynamic_slots.template
lsst/ctrl/platform/s3df/etc/templates/generic.slurm.template
lsst/ctrl/platform/s3df/etc/templates/glidein_condor_config.template
lsst_ctrl_platform_s3df-30.2026.300.dist-info/METADATA
lsst_ctrl_platform_s3df-30.2026.300.dist-info/WHEEL
lsst_ctrl_platform_s3df-30.2026.300.dist-info/licenses/LICENSE
lsst_ctrl_platform_s3df-30.2026.300.dist-info/RECORD
