Metadata-Version: 2.4
Name: lsst-ctrl-platform-s3df
Version: 30.2026.300
Summary: Configuration and template files for s3df ctrl-execute platform.
Project-URL: Source, https://github.com/lsst/ctrl_platform_s3df
Author-email: Rubin Observatory Data Management <dm-admin@lists.lsst.org>
License-File: LICENSE
Keywords: lsst
Classifier: Intended Audience :: Science/Research
Classifier: License :: OSI Approved :: BSD License
Classifier: Operating System :: OS Independent
Classifier: Programming Language :: Python :: 3
Classifier: Programming Language :: Python :: 3.11
Classifier: Programming Language :: Python :: 3.12
Classifier: Programming Language :: Python :: 3.13
Classifier: Topic :: Scientific/Engineering :: Astronomy
Requires-Python: >=3.11
